Metadata-Version: 2.1
Name: lyyplugin
Version: 1.2
Summary: userfull application for  lyy
Author: lyy
Author-email: beyondcy@gmail.com
License: MIT
License-File: LICENSE
